{
  "collectionName": "components_iso_component_subsections",
  "info": {
    "name": "Subsection",
    "icon": "align-justify"
  },
  "options": {},
  "attributes": {
    "enumerator": {
      "type": "string"
    },
    "description": {
      "type": "string"
    },
    "tag": {
      "type": "component",
      "repeatable": false,
      "component": "iso-components.tag"
    },
    "annex": {
      "type": "component",
      "repeatable": true,
      "component": "iso-components.annex"
    }
  }
}
